{
  "name": "HEADQUARTERS",
  "arena": 36,
  "theme": "office",
  "blocks": [
    [
      -20,
      -12,
      20,
      1.2,
      5,
      "wall"
    ],
    [
      10,
      -12,
      16,
      1.2,
      5,
      "wall"
    ],
    [
      28,
      -12,
      8,
      1.2,
      5,
      "wall"
    ],
    [
      20,
      12,
      20,
      1.2,
      5,
      "wall"
    ],
    [
      -10,
      12,
      16,
      1.2,
      5,
      "wall"
    ],
    [
      -28,
      12,
      8,
      1.2,
      5,
      "wall"
    ],
    [
      -12,
      0,
      1.2,
      16,
      5,
      "wall"
    ],
    [
      12,
      0,
      1.2,
      16,
      5,
      "wall"
    ],
    [
      -24,
      -24,
      1.2,
      16,
      5,
      "wall"
    ],
    [
      24,
      24,
      1.2,
      16,
      5,
      "wall"
    ],
    [
      0,
      -27,
      1.2,
      10,
      5,
      "wall"
    ],
    [
      0,
      27,
      1.2,
      10,
      5,
      "wall"
    ],
    [
      -18,
      -18,
      2.2,
      2.2,
      2.2,
      "crate"
    ],
    [
      18,
      18,
      2.2,
      2.2,
      2.2,
      "crate"
    ],
    [
      -6,
      -20,
      2.2,
      2.2,
      2.2,
      "crate"
    ],
    [
      6,
      20,
      2.2,
      2.2,
      2.2,
      "crate"
    ],
    [
      -20,
      6,
      2.2,
      2.2,
      2.2,
      "crate"
    ],
    [
      20,
      -6,
      2.2,
      2.2,
      2.2,
      "crate"
    ],
    [
      -30,
      30,
      2.2,
      2.2,
      2.2,
      "crate"
    ],
    [
      30,
      -30,
      2.2,
      2.2,
      2.2,
      "crate"
    ]
  ],
  "spawns": [
    [
      -34,
      -34
    ],
    [
      34,
      34
    ],
    [
      -34,
      34
    ],
    [
      34,
      -34
    ],
    [
      0,
      -34
    ],
    [
      0,
      34
    ],
    [
      -34,
      0
    ],
    [
      34,
      0
    ]
  ],
  "pickups": [
    {
      "kind": "rifle",
      "x": 0,
      "z": 0
    },
    {
      "kind": "shotgun",
      "x": 0,
      "z": 18
    },
    {
      "kind": "sniper",
      "x": -30,
      "z": 0
    },
    {
      "kind": "armor",
      "x": 14,
      "z": -14
    },
    {
      "kind": "armor",
      "x": -14,
      "z": 14
    },
    {
      "kind": "ammo",
      "x": 26,
      "z": 26
    },
    {
      "kind": "ammo",
      "x": -26,
      "z": -26
    },
    {
      "kind": "ammo",
      "x": 26,
      "z": -26
    },
    {
      "kind": "ammo",
      "x": -26,
      "z": 26
    },
    {
      "kind": "mines",
      "x": 0,
      "z": -6
    },
    {
      "kind": "mines",
      "x": 0,
      "z": 6
    }
  ]
}